torch/redstone/__init__.py
torch_redstone/__init__.py
torch_redstone/dtr.py
torch_redstone/hooking.py
torch_redstone/lib.py
torch_redstone/log.py
torch_redstone/loop.py
torch_redstone/loss.py
torch_redstone/metric.py
torch_redstone/polyfill.py
torch_redstone/processor.py
torch_redstone/task.py
torch_redstone/types.py
torch_redstone/utils.py
torch_redstone/version.py
torch.redstone-0.0.6.dist-info/LICENSE
torch.redstone-0.0.6.dist-info/METADATA
torch.redstone-0.0.6.dist-info/WHEEL
torch.redstone-0.0.6.dist-info/top_level.txt
torch.redstone-0.0.6.dist-info/RECORD
