Metadata-Version: 2.1
Name: torch.redstone
Version: 0.0.6
Summary: Redstone torch, common boilerplates for PyTorch.
Home-page: https://github.com/eliphatfs/torch.redstone
Author: flandre.info
Author-email: flandre@scarletx.cn
License: UNKNOWN
Platform: UNKNOWN
Classifier: Programming Language :: Python :: 3 :: Only
Classifier: License :: OSI Approved :: Apache Software License
Classifier: Operating System :: OS Independent
Requires-Python: ~=3.6
Requires-Dist: numpy
Requires-Dist: tqdm
Requires-Dist: typing-extensions
